Workbook

Sheet Supuestos
A1: Supuestos del modelo (celdas amarillas = editables). Fecha de referencia: 22-10-2026
A3: Parámetro | B3: Valor | C3: Descripción
A4: cuota_creador | B4: 0.7 | C4: Parte de los Robux gastados que recibe el creador (pases y productos)
A5: devex_estandar | B5: 0.0038 | C5: USD por Earned Robux (desde 05-09-2025)
A6: devex_18us | B6: 0.0054 | C6: USD por Earned Robux elegible de EE. UU. 18+ (desde 08-06-2026)
A7: eurusd | B7: 1.1215 | C7: USD por EUR, BCE 20-10-2026
A8: recompensa_diaria | B8: 5 | C8: R$ por usuario cualificado/día (Creator Rewards)
A9: dias_mes | B9: 30.4 | C9: Días por mes
A10: sesiones_dia | B10: 1.6 | C10: HIPÓTESIS: sesiones por DAU y día
A11: minutos_sesion | B11: 14 | C11: HIPÓTESIS: minutos por sesión
A12: conversion | B12: 0.025 | C12: HIPÓTESIS: % de DAU que paga en el día (monetización media)
A13: arppu_rs | B13: 60 | C13: HIPÓTESIS: R$ brutos por pagador y día
A14: cualificados_cr | B14: 0.05 | C14: HIPÓTESIS: % de DAU que cuenta para Creator Rewards
A15: cuota_18us | B15: 0.05 | C15: HIPÓTESIS: % de Earned Robux de compras a la tasa 18+ EE. UU.
... A22: cpp_usd | B22: 0.03 | C22: HIPÓTESIS: USD por partida en Ads Manager
A24: Derivados
A25: dau_por_ccu | B25: =1440/(Supuestos!$B$10*Supuestos!$B$11)
A26: arpdau_rs | B26: =Supuestos!$B$12*Supuestos!$B$13
A27: usd_por_dau_dia | B27: =Supuestos!$B$26*Supuestos!$B$4*((1-Supuestos!$B$15)*Supuestos!$B$5+Supuestos!$B$15*Supuestos!$B$6)+Supuestos!$B$14*Supuestos!$B$8*Supuestos!$B$5
A28: eur_por_ccu_mes | B28: =Supuestos!$B$25*Supuestos!$B$27*Supuestos!$B$9/Supuestos!$B$7
A29: costes_fijos_mes | B29: =Supuestos!$B$16+Supuestos!$B$17+Supuestos!$B$18+Supuestos!$B$19

Sheet CCU_a_ingresos
A1: Conversión CCU → ingresos con los supuestos de la hoja Supuestos (monetización media editable)
A2: CCU medio | B2: DAU | C2: Pagadores/día | D2: R$ brutos/día | E2: Earned R$/mes | F2: USD/mes | G2: EUR/mes | H2: EUR/año | I2: Costes EUR/mes | J2: Beneficio operativo EUR/mes | K2: Por socio EUR/mes | L2: Beneficio con coste oportunidad
A3: 10 | B3: =A3*Supuestos!$B$25 | C3: =B3*Supuestos!$B$12 | D3: =B3*Supuestos!$B$26 | E3: =(D3*Supuestos!$B$4+B3*Supuestos!$B$14*Supuestos!$B$8)*Supuestos!$B$9 | F3: =B3*Supuestos!$B$27*Supuestos!$B$9 | G3: =F3/Supuestos!$B$7 | H3: =G3*12 | I3: =Supuestos!$B$29+IF(G3>=10000,0.15*G3,IF(G3>=3000,0.1*G3,0)) | J3: =G3-I3 | K3: =J3/2 | L3: =J3-Supuestos!$B$20*Supuestos!$B$21
A4: 50 | B4: =A4*Supuestos!$B$25 | C4: =B4*Supuestos!$B$12 | D4: =B4*Supuestos!$B$26 | E4: =(D4*Supuestos!$B$4+B4*Supuestos!$B$14*Supuestos!$B$8)*Supuestos!$B$9 | F4: =B4*Supuestos!$B$27*Supuestos!$B$9 | G4: =F4/Supuestos!$B$7 | H4: =G4*12 | I4: =Supuestos!$B$29+IF(G4>=10000,0.15*G4,IF(G4>=3000,0.1*G4,0)) | J4: =G4-I4 | K4: =J4/2 | L4: =J4-Supuestos!$B$20*Supuestos!$B$21
A5: 100 | B5: =A5*Supuestos!$B$25 | C5: =B5*Supuestos!$B$12 | D5: =B5*Supuestos!$B$26 | E5: =(D5*Supuestos!$B$4+B5*Supuestos!$B$14*Supuestos!$B$8)*Supuestos!$B$9 | F5: =B5*Supuestos!$B$27*Supuestos!$B$9 | G5: =F5/Supuestos!$B$7 | H5: =G5*12 | I5: =Supuestos!$B$29+IF(G5>=10000,0.15*G5,IF(G5>=3000,0.1*G5,0)) | J5: =G5-I5 | K5: =J5/2 | L5: =J5-Supuestos!$B$20*Supuestos!$B$21
A6: 250 | B6: =A6*Supuestos!$B$25 | C6: =B6*Supuestos!$B$12 | D6: =B6*Supuestos!$B$26 | E6: =(D6*Supuestos!$B$4+B6*Supuestos!$B$14*Supuestos!$B$8)*Supuestos!$B$9 | F6: =B6*Supuestos!$B$27*Supuestos!$B$9 | G6: =F6/Supuestos!$B$7 | H6: =G6*12 | I6: =Supuestos!$B$29+IF(G6>=10000,0.15*G6,IF(G6>=3000,0.1*G6,0)) | J6: =G6-I6 | K6: =J6/2 | L6: =J6-Supuestos!$B$20*Supuestos!$B$21
A7: 500 | B7: =A7*Supuestos!$B$25 | C7: =B7*Supuestos!$B$12 | D7: =B7*Supuestos!$B$26 | E7: =(D7*Supuestos!$B$4+B7*Supuestos!$B$14*Supuestos!$B$8)*Supuestos!$B$9 | F7: =B7*Supuestos!$B$27*Supuestos!$B$9 | G7: =F7/Supuestos!$B$7 | H7: =G7*12 | I7: =Supuestos!$B$29+IF(G7>=10000,0.15*G7,IF(G7>=3000,0.1*G7,0)) | J7: =G7-I7 | K7: =J7/2 | L7: =J7-Supuestos!$B$20*Supuestos!$B$21
A8: 1000 | B8: =A8*Supuestos!$B$25 | C8: =B8*Supuestos!$B$12 | D8: =B8*Supuestos!$B$26 | E8: =(D8*Supuestos!$B$4+B8*Supuestos!$B$14*Supuestos!$B$8)*Supuestos!$B$9 | F8: =B8*Supuestos!$B$27*Supuestos!$B$9 | G8: =F8/Supuestos!$B$7 | H8: =G8*12 | I8: =Supuestos!$B$29+IF(G8>=10000,0.15*G8,IF(G8>=3000,0.1*G8,0)) | J8: =G8-I8 | K8: =J8/2 | L8: =J8-Supuestos!$B$20*Supuestos!$B$21
A9: 2000 | B9: =A9*Supuestos!$B$25 | C9: =B9*Supuestos!$B$12 | D9: =B9*Supuestos!$B$26 | E9: =(D9*Supuestos!$B$4+B9*Supuestos!$B$14*Supuestos!$B$8)*Supuestos!$B$9 | F9: =B9*Supuestos!$B$27*Supuestos!$B$9 | G9: =F9/Supuestos!$B$7 | H9: =G9*12 | I9: =Supuestos!$B$29+IF(G9>=10000,0.15*G9,IF(G9>=3000,0.1*G9,0)) | J9: =G9-I9 | K9: =J9/2 | L9: =J9-Supuestos!$B$20*Supuestos!$B$21
A10: 5000 | B10: =A10*Supuestos!$B$25 | C10: =B10*Supuestos!$B$12 | D10: =B10*Supuestos!$B$26 | E10: =(D10*Supuestos!$B$4+B10*Supuestos!$B$14*Supuestos!$B$8)*Supuestos!$B$9 | F10: =B10*Supuestos!$B$27*Supuestos!$B$9 | G10: =F10/Supuestos!$B$7 | H10: =G10*12 | I10: =Supuestos!$B$29+IF(G10>=10000,0.15*G10,IF(G10>=3000,0.1*G10,0)) | J10: =G10-I10 | K10: =J10/2 | L10: =J10-Supuestos!$B$20*Supuestos!$B$21
A11: 10000 | B11: =A11*Supuestos!$B$25 | C11: =B11*Supuestos!$B$12 | D11: =B11*Supuestos!$B$26 | E11: =(D11*Supuestos!$B$4+B11*Supuestos!$B$14*Supuestos!$B$8)*Supuestos!$B$9 | F11: =B11*Supuestos!$B$27*Supuestos!$B$9 | G11: =F11/Supuestos!$B$7 | H11: =G11*12 | I11: =Supuestos!$B$29+IF(G11>=10000,0.15*G11,IF(G11>=3000,0.1*G11,0)) | J11: =G11-I11 | K11: =J11/2 | L11: =J11-Supuestos!$B$20*Supuestos!$B$21
A12: 25000 | B12: =A12*Supuestos!$B$25 | C12: =B12*Supuestos!$B$12 | D12: =B12*Supuestos!$B$26 | E12: =(D12*Supuestos!$B$4+B12*Supuestos!$B$14*Supuestos!$B$8)*Supuestos!$B$9 | F12: =B12*Supuestos!$B$27*Supuestos!$B$9 | G12: =F12/Supuestos!$B$7 | H12: =G12*12 | I12: =Supuestos!$B$29+IF(G12>=10000,0.15*G12,IF(G12>=3000,0.1*G12,0)) | J12: =G12-I12 | K12: =J12/2 | L12: =J12-Supuestos!$B$20*Supuestos!$B$21

Sheet Objetivos_ingresos
A1: CCU y DAU necesarios para cada objetivo de ingresos netos mensuales (antes de costes)
A2: Objetivo EUR/mes | B2: CCU medio necesario | C2: DAU necesario | D2: Pagadores/día | E2: Nuevos/día (días de vida editables) | F2: Días de vida por usuario (365 d)
A3: 100 | B3: =A3/Supuestos!$B$28 | C3: =B3*Supuestos!$B$25 | D3: =C3*Supuestos!$B$12 | E3: =C3/F3 | F3: 2.78
A4: 500 | B4: =A4/Supuestos!$B$28 | C4: =B4*Supuestos!$B$25 | D4: =C4*Supuestos!$B$12 | E4: =C4/F4 | F4: 2.78
A5: 1000 | B5: =A5/Supuestos!$B$28 | C5: =B5*Supuestos!$B$25 | D5: =C5*Supuestos!$B$12 | E5: =C5/F5 | F5: 2.78
A6: 3000 | B6: =A6/Supuestos!$B$28 | C6: =B6*Supuestos!$B$25 | D6: =C6*Supuestos!$B$12 | E6: =C6/F6 | F6: 2.78
A7: 5000 | B7: =A7/Supuestos!$B$28 | C7: =B7*Supuestos!$B$25 | D7: =C7*Supuestos!$B$12 | E7: =C7/F7 | F7: 2.78
A8: 10000 | B8: =A8/Supuestos!$B$28 | C8: =B8*Supuestos!$B$25 | D8: =C8*Supuestos!$B$12 | E8: =C8/F8 | F8: 2.78
A9: 25000 | B9: =A9/Supuestos!$B$28 | C9: =B9*Supuestos!$B$25 | D9: =C9*Supuestos!$B$12 | E9: =C9/F9 | F9: 2.78
A10: 50000 | B10: =A10/Supuestos!$B$28 | C10: =B10*Supuestos!$B$25 | D10: =C10*Supuestos!$B$12 | E10: =C10/F10 | F10: 2.78

Sheet Simulador_cohortes
A1: Simulador mensual: edita los nuevos usuarios/día de cada mes y el núcleo de retención
A2: El núcleo K(a) es el DAU medio en el mes a generado por 1 usuario nuevo/día durante un mes (precalculado desde la curva diaria).
A3: Edad (meses) | B3: 0 | C3: 1 | D3: 2 | E3: 3 | F3: 4 | G3: 5 | H3: 6 | I3: 7 | J3: 8 | K3: 9 | L3: 10 | M3: 11 | N3: 12 | O3: 13 | P3: 14 | Q3: 15 | R3: 16 | S3: 17 | T3: 18 | U3: 19 | V3: 20 | W3: 21 | X3: 22 | Y3: 23
A4: K pesimista | B4: 1.19923 | C4: 0.11337 | D4: 0.05216 | E4: 0.03645 | F4: 0.02852 | G4: 0.02363 | H4: 0.02032 | I4: 0.01786 | J4: 0.01598 | K4: 0.01448 | L4: 0.01327 | M4: 0.01227 | N4: 0.01141 | O4: 0.01068 | P4: 0.01004 | Q4: 0.00948 | R4: 0.00899 | S4: 0.00855 | T4: 0.00815 | U4: 0.00779 | V4: 0.00747 | W4: 0.00718 | X4: 0.0069 | Y4: 0.00665
A5: K base | B5: 1.50841 | C5: 0.36162 | D5: 0.18211 | E5: 0.13143 | F5: 0.1051 | G5: 0.08851 | H5: 0.07716 | I5: 0.06859 | J5: 0.06195 | K5: 0.05664 | L5: 0.05228 | M5: 0.04869 | N5: 0.04557 | O5: 0.04288 | P5: 0.04054 | Q5: 0.03847 | R5: 0.03666 | S5: 0.03502 | T5: 0.03353 | U5: 0.03218 | V5: 0.03096 | W5: 0.02985 | X5: 0.02881 | Y5: 0.02786
A6: K optimista | B6: 1.94432 | C6: 0.8532 | D6: 0.50274 | E6: 0.3882 | F6: 0.32499 | G6: 0.28346 | H6: 0.2541 | I6: 0.23137 | J6: 0.21334 | K6: 0.19865 | L6: 0.18636 | M6: 0.17608 | N6: 0.16705 | O6: 0.15915 | P6: 0.15218 | Q6: 0.14596 | R6: 0.14047 | S6: 0.13541 | T6: 0.13081 | U6: 0.12661 | V6: 0.12275 | W6: 0.11924 | X6: 0.11594 | Y6: 0.11286
A7: K excepcional | B7: 2.48353 | C7: 1.5055 | D7: 0.93667 | E7: 0.7402 | F7: 0.6295 | G7: 0.55573 | H7: 0.50301 | I7: 0.4618 | J7: 0.42887 | K7: 0.40185 | L7: 0.37913 | M7: 0.36 | N7: 0.34312 | O7: 0.32829 | P7: 0.31515 | Q7: 0.30339 | R7: 0.29295 | S7: 0.28332 | T7: 0.27453 | U7: 0.26648 | V7: 0.25905 | W7: 0.25229 | X7: 0.24591 | Y7: 0.23996
A8: K usado (editable) | B8: =B5 | C8: =C5 | D8: =D5 | E8: =E5 | F8: =F5 | G8: =G5 | H8: =H5 | I8: =I5 | ... Y8: =Y5
A10: Mes | B10: 1 | C10: 2 | D10: 3 | E10: 4 | F10: 5 | G10: 6 | H10: 7 | I10: 8 | J10: 9 | K10: 10 | L10: 11 | M10: 12 | N10: 13 | O10: 14 | P10: 15 | Q10: 16 | R10: 17 | S10: 18 | T10: 19 | U10: 20 | V10: 21 | W10: 22 | X10: 23 | Y10: 24
A11: Nuevos usuarios/día (media del mes) | B11: 2451 | C11: 1360 | D11: 1341 | E11: 1228 | F11: 1230 | G11: 1156 | H11: 1132 | I11: 1098 | J11: 1044 | K11: 1028 | L11: 768 | M11: 793 | N11: 737 | O11: 753 | P11: 715 | Q11: 715 | R11: 697 | S11: 681 | T11: 685 | U11: 651 | V11: 677 | W11: 638 | X11: 658 | Y11: 628
A12: DAU medio | B12: =B11*B8 | C12: =B11*C8+C11*B8 | D12: =B11*D8+C11*C8+D11*B8 | E12: =B11*E8+C11*D8+D11*C8+E11*B8 | F12: =B11*F8+C11*E8+D11*D8+E11*C8+F11*B8 | G12: =B11*G8+C11*F8+D11*E8+E11*D8+F11*C8+G11*B8 | H12: =B11*H8+C11*G8+D11*F8+E11*E8+F11*D8+G11*C8+H11*B8 | I12: =B11*I8+C11*H8+D11*G8+E11*F8+F11*E8+G11*D8+H11*C8+I11*B8 | J12: =B11*J8+C11*I8+D11*H8+E11*G8+F11*F8+G11*E8+H11*D8+I11*C8+J11*B8 | K12: =B11*K8+C11*J8+D11*I8+E11*H8+F11*G8+G11*F8+H11*E8+I11*D8+J11*C8+K11*B8 | L12: =B11*L8+C11*K8+D11*J8+E11*I8+F11*H8+G11*G8+H11*F8+I11*E8+J11*D8+K11*C8+L11*B8 | M12: =B11*M8+C11*L8+D11*K8+E11*J8+F11*I8+G11*H8+H11*G8+I11*F8+J11*E8+K11*D8+L11*C8+M11*B8 | N12: =B11*N8+C11*M8+D11*L8+E11*K8+F11*J8+G11*I8+H11*H8+I11*G8+J11*F8+K11*E8+L11*D8+M11*C8+N11*B8 | O12: =B11*O8+C11*N8+D11*M8+E11*L8+F11*K8+G11*J8+H11*I8+I11*H8+J11*G8+K11*F8+L11*E8+M11*D8+N11*C8+O11*B8 | P12: =B11*P8+C11*O8+D11*N8+E11*M8+F11*L8+G11*K8+H11*J8+I11*I8+J11*H8+K11*G8+L11*F8+M11*E8+N11*D8+O11*C8+P11*B8 | Q12: =B11*Q8+C11*P8+D11*O8+E11*N8+F11*M8+G11*L8+H11*K8+I11*J8+J11*I8+K11*H8+L11*G8+M11*F8+N11*E8+O11*D8+P11*C8+Q11*B8 | R12: =B11*R8+C11*Q8+D11*P8+E11*O8+F11*N8+G11*M8+H11*L8+I11*K8+J11*J8+K11*I8+L11*H8+M11*G8+N11*F8+O11*E8+P11*D8+Q11*C8+R11*B8 | S12: =B11*S8+C11*R8+D11*Q8+E11*P8+F11*O8+G11*N8+H11*M8+I11*L8+J11*K8+K11*J8+L11*I8+M11*H8+N11*G8+O11*F8+P11*E8+Q11*D8+R11*C8+S11*B8 | T12: =B11*T8+C11*S8+D11*R8+E11*Q8+F11*P8+G11*O8+H11*N8+I11*M8+J11*L8+K11*K8+L11*J8+M11*I8+N11*H8+O11*G8+P11*F8+Q11*E8+R11*D8+S11*C8+T11*B8 | U12: =B11*U8+C11*T8+D11*S8+E11*R8+F11*Q8+G11*P8+H11*O8+I11*N8+J11*M8+K11*L8+L11*K8+M11*J8+N11*I8+O11*H8+P11*G8+Q11*F8+R11*E8+S11*D8+T11*C8+U11*B8 | V12: =B11*V8+C11*U8+D11*T8+E11*S8+F11*R8+G11*Q8+H11*P8+I11*O8+J11*N8+K11*M8+L11*L8+M11*K8+N11*J8+O11*I8+P11*H8+Q11*G8+R11*F8+S11*E8+T11*D8+U11*C8+V11*B8 | W12: =B11*W8+C11*V8+D11*U8+E11*T8+F11*S8+G11*R8+H11*Q8+I11*P8+J11*O8+K11*N8+L11*M8+M11*L8+N11*K8+O11*J8+P11*I8+Q11*H8+R11*G8+S11*F8+T11*E8+U11*D8+V11*C8+W11*B8 | X12: =B11*X8+C11*W8+D11*V8+E11*U8+F11*T8+G11*S8+H11*R8+I11*Q8+J11*P8+K11*O8+L11*N8+M11*M8+N11*L8+O11*K8+P11*J8+Q11*I8+R11*H8+S11*G8+T11*F8+U11*E8+V11*D8+W11*C8+X11*B8 | Y12: =B11*Y8+C11*X8+D11*W8+E11*V8+F11*U8+G11*T8+H11*S8+I11*R8+J11*Q8+K11*P8+L11*O8+M11*N8+N11*M8+O11*L8+P11*K8+Q11*J8+R11*I8+S11*H8+T11*G8+U11*F8+V11*E8+W11*D8+X11*C8+Y11*B8
A13: CCU medio | B13: =B12*Supuestos!$B$10*Supuestos!$B$11/1440 | C13: =C12*Supuestos!$B$10*Supuestos!$B$11/1440 | D13: =D12*Supuestos!$B$10*Supuestos!$B$11/1440 | E13: =E12*Supuestos!$B$10*Supuestos!$B$11/1440 | F13: =F12*Supuestos!$B$10*Supuestos!$B$11/1440 | G13: =G12*Supuestos!$B$10*Supuestos!$B$11/1440 | H13: =H12*Supuestos!$B$10*Supuestos!$B$11/1440 | I13: =I12*Supuestos!$B$10*Supuestos!$B$11/1440 | ... Y13: =Y12*Supuestos!$B$10*Supuestos!$B$11/1440
A14: Ingresos EUR/mes | B14: =B12*Supuestos!$B$27*Supuestos!$B$9/Supuestos!$B$7 | C14: =C12*Supuestos!$B$27*Supuestos!$B$9/Supuestos!$B$7 | D14: =D12*Supuestos!$B$27*Supuestos!$B$9/Supuestos!$B$7 | E14: =E12*Supuestos!$B$27*Supuestos!$B$9/Supuestos!$B$7 | F14: =F12*Supuestos!$B$27*Supuestos!$B$9/Supuestos!$B$7 | G14: =G12*Supuestos!$B$27*Supuestos!$B$9/Supuestos!$B$7 | H14: =H12*Supuestos!$B$27*Supuestos!$B$9/Supuestos!$B$7 | I14: =I12*Supuestos!$B$27*Supuestos!$B$9/Supuestos!$B$7 | ... Y14: =Y12*Supuestos!$B$27*Supuestos!$B$9/Supuestos!$B$7
A15: Costes EUR/mes | B15: =Supuestos!$B$29+IF(B14>=10000,0.15*B14,IF(B14>=3000,0.1*B14,0)) | C15: =Supuestos!$B$29+IF(C14>=10000,0.15*C14,IF(C14>=3000,0.1*C14,0)) | D15: =Supuestos!$B$29+IF(D14>=10000,0.15*D14,IF(D14>=3000,0.1*D14,0)) | E15: =Supuestos!$B$29+IF(E14>=10000,0.15*E14,IF(E14>=3000,0.1*E14,0)) | F15: =Supuestos!$B$29+IF(F14>=10000,0.15*F14,IF(F14>=3000,0.1*F14,0)) | G15: =Supuestos!$B$29+IF(G14>=10000,0.15*G14,IF(G14>=3000,0.1*G14,0)) | H15: =Supuestos!$B$29+IF(H14>=10000,0.15*H14,IF(H14>=3000,0.1*H14,0)) | I15: =Supuestos!$B$29+IF(I14>=10000,0.15*I14,IF(I14>=3000,0.1*I14,0)) | ... Y15: =Supuestos!$B$29+IF(Y14>=10000,0.15*Y14,IF(Y14>=3000,0.1*Y14,0))
A16: Beneficio operativo EUR/mes | B16: =B14-B15 | C16: =C14-C15 | D16: =D14-D15 | E16: =E14-E15 | F16: =F14-F15 | G16: =G14-G15 | H16: =H14-H15 | I16: =I14-I15 | ... Y16: =Y14-Y15
A17: Inversión previa EUR | B17: 2560
A18: Caja acumulada EUR | B18: =SUM($B$16:B16)-$B$17 | C18: =SUM($B$16:C16)-$B$17 | D18: =SUM($B$16:D16)-$B$17 | E18: =SUM($B$16:E16)-$B$17 | F18: =SUM($B$16:F16)-$B$17 | G18: =SUM($B$16:G16)-$B$17 | H18: =SUM($B$16:H16)-$B$17 | I18: =SUM($B$16:I16)-$B$17 | ... Y18: =SUM($B$16:Y16)-$B$17

Sheet Escenarios_24m
A1: Resultados de la simulación diaria por cohortes (valores generados por modelo.py)
A2: escenario | B2: mes | C2: nuevos_dia_medio | D2: dau_medio | E2: ccu_medio | F2: ccu_pico_semanal_est | G2: ingresos_usd | H2: marketing_eur | I2: ingresos_eur | J2: costes_eur | K2: beneficio_operativo_eur | L2: caja_acumulada_eur | M2: por_socio_eur | N2: resultado_con_coste_oportunidad_eur
A3: pesimista | B3: 1 | C3: 391.49 | D3: 481.98 | E3: 5.15 | F3: 7.93 | G3: 32.36 | H3: 50 | I3: 28.86 | J3: 300 | K3: -271.14 | L3: -2581.14 | M3: -135.57 | N3: -1771.14
A4: pesimista | B4: 2 | C4: 141.9 | D4: 208.4 | E4: 2.23 | F4: 3.43 | G4: 13.54 | H4: 0 | I4: 12.07 | J4: 250 | K4: -237.93 | L4: -2819.07 | M4: -118.96 | N4: -1737.93
A5: pesimista | B5: 3 | C5: 122.71 | D5: 182.69 | E5: 1.95 | F5: 3.01 | G5: 12.27 | H5: 0 | I5: 10.94 | J5: 250 | K5: -239.06 | L5: -3058.13 | M5: -119.53 | N5: -1739.06
A6: pesimista | B6: 4 | C6: 111.42 | D6: 169.1 | E6: 1.81 | F6: 2.78 | G6: 10.99 | H6: 0 | I6: 9.8 | J6: 250 | K6: -240.2 | L6: -3298.33 | M6: -120.1 | N6: -1740.2
A7: pesimista | B7: 5 | C7: 102.91 | D7: 158.98 | E7: 1.7 | F7: 2.62 | G7: 10.33 | H7: 0 | I7: 9.21 | J7: 250 | K7: -240.79 | L7: -3539.12 | M7: -120.39 | N7: -1740.79
A8: pesimista | B8: 6 | C8: 95.96 | D8: 150.55 | E8: 1.61 | F8: 2.48 | G8: 10.11 | H8: 0 | I8: 9.01 | J8: 250 | K8: -240.99 | L8: -3780.11 | M8: -120.49 | N8: -1740.99
A9: pesimista | B9: 7 | C9: 88.86 | D9: 141.96 | E9: 1.52 | F9: 2.34 | G9: 9.22 | H9: 0 | I9: 8.22 | J9: 250 | K9: -241.78 | L9: -4021.88 | M9: -120.89 | N9: -1741.78
A10: pesimista | B10: 8 | C10: 83.58 | D10: 135.33 | E10: 1.45 | F10: 2.23 | G10: 9.09 | H10: 0 | I10: 8.1 | J10: 250 | K10: -241.9 | L10: -4263.78 | M10: -120.95 | N10: -1741.9
A11: pesimista | B11: 9 | C11: 74.58 | D11: 124.71 | E11: 1.33 | F11: 2.05 | G11: 8.1 | H11: 0 | I11: 7.23 | J11: 250 | K11: -242.77 | L11: -4506.55 | M11: -121.39 | N11: -1742.77
A12: pesimista | B12: 10 | C12: 51.89 | D12: 95.89 | E12: 1.03 | F12: 1.58 | G12: 6.23 | H12: 0 | I12: 5.56 | J12: 250 | K12: -244.44 | L12: -4751 | M12: -122.22 | N12: -1744.44
A13: pesimista | B13: 11 | C13: 49.46 | D13: 90.55 | E13: 0.97 | F13: 1.49 | G13: 6.08 | H13: 0 | I13: 5.42 | J13: 250 | K13: -244.58 | L13: -4995.58 | M13: -122.29 | N13: -1744.58
A14: pesimista | B14: 12 | C14: 47.02 | D14: 86.25 | E14: 0.92 | F14: 1.42 | G14: 5.6 | H14: 0 | I14: 5 | J14: 250 | K14: -245 | L14: -5240.58 | M14: -122.5 | N14: -1745
... A98: excepcional | B98: 24 | C98: 7108.28 | D98: 131823.4 | E98: 3130.81 | F98: 4816.53 | G98: 19868.42 | H98: 493.42 | I98: 17715.94 | J98: 3400.81 | K98: 14315.12 | L98: 353704.32 | M98: 7157.56 | N98: 12815.12

Sheet Matriz_conceptos
A1: Matriz de decisión ponderada (edita pesos y puntuaciones)
A2: Criterio | B2: Peso | C2: C1 Carreras callejeras mundo abierto + reputación | D2: C2 Arcade de personalización / car meets | E2: C3 PvP clasificatorio por temporadas | F2: C4 De coche barato a hiperdeportivo (colección/tycoon) | G2: C5 Mundo abierto social / roleplay | H2: C6 Street racing por crews + persecuciones (híbrido)
A3: Facilidad de captación (CTR/PTR) | B3: 10 | C3: 8 | D3: 6 | E3: 5 | F3: 7 | G3: 7 | H3: 7
A4: Potencial de retención (D1-D28) | B4: 16 | C4: 6 | D4: 5 | E4: 6 | F4: 7 | G4: 6 | H4: 8
A5: Potencial de monetización | B5: 12 | C5: 7 | D5: 8 | E5: 4 | F5: 8 | G5: 6 | H5: 7
A6: Viralidad y co-juego | B6: 8 | C6: 6 | D6: 7 | E6: 6 | F6: 4 | G6: 5 | H6: 8
A7: Originalidad / diferenciación | B7: 8 | C7: 5 | D7: 6 | E7: 6 | F7: 3 | G7: 2 | H7: 8
A8: Viabilidad técnica (inversa a complejidad) | B8: 10 | C8: 4 | D8: 6 | E8: 5 | F8: 6 | G8: 3 | H8: 5
A9: Contenido necesario (inverso) | B9: 8 | C9: 4 | D9: 5 | E9: 7 | F9: 4 | G9: 3 | H9: 6
A10: Tiempo de desarrollo (inverso) | B10: 8 | C10: 4 | D10: 6 | E10: 7 | F10: 6 | G10: 3 | H10: 6
A11: Riesgo de ejecución (inverso) | B11: 6 | C11: 5 | D11: 5 | E11: 4 | F11: 5 | G11: 4 | H11: 5
A12: Competencia directa (inversa) | B12: 8 | C12: 4 | D12: 6 | E12: 7 | F12: 3 | G12: 2 | H12: 7
A13: Potencial de crecimiento | B13: 6 | C13: 8 | D13: 6 | E13: 5 | F13: 6 | G13: 7 | H13: 8
A14: Puntuación 0-100 | C14: =SUMPRODUCT($B$3:$B$13,C3:C13)/SUM($B$3:$B$13)*10 | D14: =SUMPRODUCT($B$3:$B$13,D3:D13)/SUM($B$3:$B$13)*10 | E14: =SUMPRODUCT($B$3:$B$13,E3:E13)/SUM($B$3:$B$13)*10 | F14: =SUMPRODUCT($B$3:$B$13,F3:F13)/SUM($B$3:$B$13)*10 | G14: =SUMPRODUCT($B$3:$B$13,G3:G13)/SUM($B$3:$B$13)*10 | H14: =SUMPRODUCT($B$3:$B$13,H3:H13)/SUM($B$3:$B$13)*10

Sheet Economia_juego
A1: Tiempo para el primer coche de cada clase (créditos y horas; edita precios e ingresos)
A2: Clase | B2: Precio coche | C2: Ingreso/hora en clase previa | D2: Misiones (créditos/h) | E2: % en mejoras | F2: Bono inicial | G2: Horas tramo | H2: Horas acumuladas
A3: C | B3: 70000 | C3: 32000 | D3: 8000 | E3: 0.15 | F3: 15000 | G3: =(B3-F3)/((C3+D3)*(1-E3)) | H3: =SUM($G$3:G3)
A4: B | B4: 230000 | C4: 58000 | D4: 8000 | E4: 0.25 | F4: 0 | G4: =(B4-F4)/((C4+D4)*(1-E4)) | H4: =SUM($G$3:G4)
A5: A | B5: 1000000 | C5: 100000 | D5: 8000 | E5: 0.3 | F5: 0 | G5: =(B5-F5)/((C5+D5)*(1-E5)) | H5: =SUM($G$3:G5)
A6: S | B6: 4000000 | C6: 170000 | D6: 8000 | E6: 0.3 | F6: 0 | G6: =(B6-F6)/((C6+D6)*(1-E6)) | H6: =SUM($G$3:G6)

Sheet Competidores
A1: juego | B1: ccu_instantanea | C1: visitas | D1: pico_historico | E1: fuente_fecha
A2: Driving Empire | B2: 29001 | C2: 3368000000 | D2: 89566 | E2: Rolimons ~18-10-2026
A3: Emergency Hamburg | B3: 16460 | C3: 1220000000 | D3: 84100 | E3: RoWatcher, sin fecha
A4: A Dusty Trip | B4: 9375 | C4: 2500000000 | E4: Rotrends, jul-ago 2026
A5: Car Driving Indonesia | B5: 6700 | C5: 426000000 | E5: Earnaldo, jul-sep 2026 (6,7-13 k)
A6: Jailbreak | B6: 10000 | C6: 7989000000 | D6: 173000 | E6: RoWatcher/AllThingsHow, jul-ago 2026
A7: Taxi Boss | B7: 8555 | C7: 842000000 | D7: 20700 | E7: Rolimons, sin fecha
A8: WRONG WAY (rally coop) | B8: 7000 | C8: 4100000 | D8: 14000 | E8: RoWatcher, oct-2026
A9: Car Crushers 2 | B9: 5679 | C9: 1400000000 | D9: 22900 | E9: Rotrends, sin fecha
A10: Midnight Chasers | B10: 5455 | C10: 308800000 | D10: 16800 | E10: Rotrends, sep-2026
A11: Greenville | B11: 4442 | C11: 1411000000 | D11: 34133 | E11: Rolimons, sin fecha
A12: Vehicle Legends | B12: 2910 | C12: 1900000000 | D12: 29700 | E12: Rolimons/tracker, jul-2026
A13: Car Dealership Tycoon | B13: 2891 | C13: 2510000000 | D13: 66726 | E13: Rolimons, sin fecha
A14: Rally Panic! (coop) | B14: 1773 | C14: 1700000 | E14: Earnaldo, 12-10-2026
A15: Southwest Florida | B15: 1180 | C15: 779300000 | D15: 29500 | E15: Rotrends, ≤ago-2026
A16: Drive World | B16: 1063 | C16: 499000000 | D16: 24600 | E16: Rotrends, ≤ago-2026
A17: Midnight Racing: Tokyo | B17: 826 | D17: 3000 | E17: RoWatcher, 2026
A18: Project Trackday (sim) | B18: 32 | C18: 45200000 | D18: 408 | E18: RoWatcher, 2026
